README.rst
setup.cfg
setup.py
src/pynicom.py
src/pynicom.egg-info/PKG-INFO
src/pynicom.egg-info/SOURCES.txt
src/pynicom.egg-info/dependency_links.txt
src/pynicom.egg-info/entry_points.txt
src/pynicom.egg-info/requires.txt
src/pynicom.egg-info/top_level.txt