Metadata-Version: 1.1
Name: pynicom
Version: 0.3.5
Summary: A Minicom like shell in Python
Home-page: https://github.com/clobrano/pynicom.git
Author: Carlo Lobrano
Author-email: c.lobrano@gmail.com
License: MIT
Keywords: serial,minicom
Platform: UNKNOWN
Classifier: Development Status :: 4 - Beta
